pyflare
tests
