Metadata-Version: 1.1
Name: pyflare
Version: 1.1.5
Summary: An adapter for CloudFlare's client API
Home-page: https://github.com/jlinn/pyflare
Author: Joe Linn
Author-email: UNKNOWN
License: LICENSE.txt
Platform: UNKNOWN
Classifier: Intended Audience :: Developers
Classifier: Development Status :: 5 - Production/Stable
Classifier: Operating System :: OS Independent
Classifier: Programming Language :: Python
Classifier: Topic :: Internet :: WWW/HTTP
